README.md
setup.py
brynq_sdk_recruitee/__init__.py
brynq_sdk_recruitee/applicants.py
brynq_sdk_recruitee/candidates.py
brynq_sdk_recruitee/offers.py
brynq_sdk_recruitee/organization.py
brynq_sdk_recruitee/recruitee.py
brynq_sdk_recruitee/vacancies.py
brynq_sdk_recruitee.egg-info/PKG-INFO
brynq_sdk_recruitee.egg-info/SOURCES.txt
brynq_sdk_recruitee.egg-info/dependency_links.txt
brynq_sdk_recruitee.egg-info/not-zip-safe
brynq_sdk_recruitee.egg-info/requires.txt
brynq_sdk_recruitee.egg-info/top_level.txt