Metadata-Version: 1.0
Name: brynq-sdk-recruitee
Version: 2.1.1
Summary: Recruitee API SDK from BrynQ
Home-page: UNKNOWN
Author: BrynQ
Author-email: support@brynq.com
License: BrynQ License
Platform: UNKNOWN
